{
  "nightly": {
    "description": "Every commit to develop",
    "hide": false,
    "last_updated": "2025-03-05T03:24:09.000Z",
    "last_updated_url": "https://github.com/engels74/overseerr-anime/actions/runs/13667076638",
    "latest": false,
    "tags": [
      "nightly",
      "nightly-8eaae026ec04c6d681f78da07589b6fbcdb5acd7",
      "nightly-15d9344"
    ]
  },
  "release": {
    "description": "Releases",
    "hide": false,
    "last_updated": "2025-02-14T21:13:23.000Z",
    "last_updated_url": "https://github.com/engels74/overseerr-anime/actions/runs/13337510473",
    "latest": true,
    "tags": [
      "release",
      "release-1.33.2-anime",
      "release-5a9f512"
    ]
  }
}
